{
    "dirs": {
      "output": "build"
    },
    "task_libs": {
      "chefapi.ts": [
        "env_version_constraint",
        "env_vsts_variables"
      ],
      "inputs.ts": [
        "cookbook_version",
        "env_version_constraint",
        "env_vsts_variables",
        "exec_chef_client",
        "exec_inspec",
        "publish_supermarket",
        "upload_cookbook",
        "install_chefdk",
        "install_inspec"
      ],
      "utils.ts": [
        "publish_supermarket",
        "upload_cookbook",
        "install_chefdk",
        "install_inspec",
        "exec_inspec"
      ],
      "builtin.ts": [
        "cookbook_version",
        "env_version_constraint",
        "env_vsts_variables",
        "exec_chef_client",
        "exec_inspec",
        "install_chefdk",
        "install_inspec",
        "publish_supermarket",
        "upload_cookbook"
      ]
    },
    "files": {
      "task": [
        "icon.png",
        "task.json"
      ],
      "extension": [
        "vss-extension.json",
        "overview.md",
        "license.txt",
        "screenshot_env_task.png",
        "screenshot_env_parameters.png",
        "screenshot_chef_server_endpoint.png",
        "images"
      ]
    }
  }